{"busDepartureA":[{"busLineId":"1","time":"05:38"},{"busLineId":"1","time":"06:39"},{"busLineId":"1","time":"08:39"},{"busLineId":"1","time":"09:39"},{"busLineId":"1","time":"10:39"},{"busLineId":"1","time":"12:38"},{"busLineId":"1","time":"13:39"},{"busLineId":"1","time":"14:39"},{"busLineId":"1","time":"15:38"},{"busLineId":"1","time":"17:39"},{"busLineId":"1","time":"18:39"},{"busLineId":"1","time":"19:39"},{"busLineId":"1","time":"20:38"},{"busLineId":"1","time":"21:39"},{"busLineId":"1","time":"22:39"}],"busDepartureB":[{"busLineId":"1","time":"05:01"},{"busLineId":"1","time":"06:11"},{"busLineId":"1","time":"07:01"},{"busLineId":"1","time":"08:01"},{"busLineId":"1","time":"09:01"},{"busLineId":"1","time":"10:07"},{"busLineId":"1","time":"11:01"},{"busLineId":"1","time":"12:01"},{"busLineId":"1","time":"13:11"},{"busLineId":"1","time":"14:01"},{"busLineId":"1","time":"15:07"},{"busLineId":"1","time":"16:11"},{"busLineId":"1","time":"17:01"},{"busLineId":"1","time":"18:01"},{"busLineId":"1","time":"19:01"},{"busLineId":"1","time":"20:01"},{"busLineId":"1","time":"21:11"},{"busLineId":"1","time":"22:01"}]}