{"busDepartureA":[{"busLineId":"610","time":"06:34","direction":"Крагујевац-Ђурисело"},{"busLineId":"610","time":"10:24","direction":"Крагујевац-Ђурисело"},{"busLineId":"610","time":"12:18","direction":"Крагујевац-Дреновац - Ђурисело"},{"busLineId":"610","time":"16:18","direction":"Крагујевац-Дреновац - Ђурисело"},{"busLineId":"610","time":"20:53","direction":"Крагујевац-Дреновац - Ђурисело"}],"busDepartureB":[{"busLineId":"610","time":"05:01","direction":"Ђурисело-Дреновац - Крагујевац"},{"busLineId":"610","time":"06:36","direction":"Ђурисело-Дреновац - Крагујевац"},{"busLineId":"610","time":"10:31","direction":"Ђурисело-Дреновац - Крагујевац"},{"busLineId":"610","time":"12:21","direction":"Ђурисело-Крагујевац"},{"busLineId":"610","time":"16:31","direction":"Ђурисело-Крагујевац"},{"busLineId":"610","time":"20:56","direction":"Ђурисело-Крагујевац"}]}