{"busDepartureA":[{"busLineId":"16","time":"05:39"},{"busLineId":"16","time":"06:29"},{"busLineId":"16","time":"07:24"},{"busLineId":"16","time":"08:14"},{"busLineId":"16","time":"09:34"},{"busLineId":"16","time":"11:24"},{"busLineId":"16","time":"12:04"},{"busLineId":"16","time":"13:04"},{"busLineId":"16","time":"13:59"},{"busLineId":"16","time":"14:59"},{"busLineId":"16","time":"15:49"},{"busLineId":"16","time":"16:59"},{"busLineId":"16","time":"18:59"},{"busLineId":"16","time":"20:49"},{"busLineId":"16","time":"22:59"},{"busLineId":"606","time":"05:22"},{"busLineId":"606","time":"07:02"},{"busLineId":"606","time":"11:22"},{"busLineId":"606","time":"13:37"},{"busLineId":"606","time":"15:52"},{"busLineId":"606","time":"16:52"},{"busLineId":"606","time":"20:32"},{"busLineId":"608","time":"06:29"},{"busLineId":"608","time":"07:34"},{"busLineId":"608","time":"13:19"},{"busLineId":"608","time":"14:29"},{"busLineId":"608","time":"15:34"},{"busLineId":"608","time":"22:29"},{"busLineId":"611","time":"06:17"},{"busLineId":"611","time":"07:57"},{"busLineId":"611","time":"09:57"},{"busLineId":"611","time":"12:07"},{"busLineId":"611","time":"14:32"},{"busLineId":"611","time":"16:17"},{"busLineId":"611","time":"19:57"},{"busLineId":"611","time":"22:47"},{"busLineId":"613","time":"06:09"},{"busLineId":"613","time":"12:49"}],"busDepartureB":[{"busLineId":"16","time":"05:04"},{"busLineId":"16","time":"05:54"},{"busLineId":"16","time":"06:49"},{"busLineId":"16","time":"07:44"},{"busLineId":"16","time":"08:31"},{"busLineId":"16","time":"09:54"},{"busLineId":"16","time":"11:31"},{"busLineId":"16","time":"12:29"},{"busLineId":"16","time":"13:29"},{"busLineId":"16","time":"14:16"},{"busLineId":"16","time":"15:24"},{"busLineId":"16","time":"16:14"},{"busLineId":"16","time":"17:31"},{"busLineId":"16","time":"19:01"},{"busLineId":"16","time":"21:14"},{"busLineId":"16","time":"23:19"},{"busLineId":"606","time":"05:22"},{"busLineId":"606","time":"06:32"},{"busLineId":"606","time":"08:32"},{"busLineId":"606","time":"13:08"},{"busLineId":"606","time":"14:42"},{"busLineId":"606","time":"18:02"},{"busLineId":"606","time":"19:32"},{"busLineId":"608","time":"07:24"},{"busLineId":"608","time":"08:24"},{"busLineId":"608","time":"14:09"},{"busLineId":"608","time":"15:29"},{"busLineId":"608","time":"16:34"},{"busLineId":"608","time":"23:24"},{"busLineId":"611","time":"05:13"},{"busLineId":"611","time":"06:53"},{"busLineId":"611","time":"08:47"},{"busLineId":"611","time":"10:42"},{"busLineId":"611","time":"12:48"},{"busLineId":"611","time":"15:12"},{"busLineId":"611","time":"16:57"},{"busLineId":"611","time":"20:42"},{"busLineId":"611","time":"23:12"},{"busLineId":"613","time":"07:14"},{"busLineId":"613","time":"13:59"}]}