{"busDepartureA":[{"busLineId":"6","time":"06:09"},{"busLineId":"6","time":"07:19"},{"busLineId":"6","time":"08:39"},{"busLineId":"6","time":"10:39"},{"busLineId":"6","time":"12:39"},{"busLineId":"6","time":"15:39"},{"busLineId":"6","time":"17:39"},{"busLineId":"6","time":"19:39"},{"busLineId":"6","time":"21:39"},{"busLineId":"13","time":"06:47"},{"busLineId":"13","time":"08:32"},{"busLineId":"13","time":"10:17"},{"busLineId":"13","time":"12:07"},{"busLineId":"13","time":"13:52"},{"busLineId":"13","time":"15:37"},{"busLineId":"13","time":"17:22"},{"busLineId":"13","time":"19:12"},{"busLineId":"13","time":"20:52"}],"busDepartureB":[{"busLineId":"6","time":"06:15"},{"busLineId":"6","time":"07:30"},{"busLineId":"6","time":"09:10"},{"busLineId":"6","time":"11:10"},{"busLineId":"6","time":"13:10"},{"busLineId":"6","time":"16:10"},{"busLineId":"6","time":"18:10"},{"busLineId":"6","time":"20:10"},{"busLineId":"13","time":"06:55"},{"busLineId":"13","time":"08:40"},{"busLineId":"13","time":"10:30"},{"busLineId":"13","time":"12:15"},{"busLineId":"13","time":"14:00"},{"busLineId":"13","time":"15:45"},{"busLineId":"13","time":"17:30"},{"busLineId":"13","time":"19:15"},{"busLineId":"13","time":"21:00"}]}