{"busDepartureA":[{"busLineId":"26","time":"05:36","direction":"Мале Пчелице (С. Село)-Теферич (Викенд Нас.)"},{"busLineId":"26","time":"06:26","direction":"Мале Пчелице (С. Село)-Теферич (Викенд Нас.)"},{"busLineId":"26","time":"07:31","direction":"Мале Пчелице (С. Село)-Теферич (Викенд Нас.)"},{"busLineId":"26","time":"08:21","direction":"Мале Пчелице (С. Село)-Теферич (Викенд Нас.)"},{"busLineId":"26","time":"09:21","direction":"Мале Пчелице (С. Село)-Теферич (Викенд Нас.)"},{"busLineId":"26","time":"11:11","direction":"Мале Пчелице (С. Село)-Теферич (Викенд Нас.)"},{"busLineId":"26","time":"13:01","direction":"Мале Пчелице (С. Село)-Теферич (Викенд Нас.)"},{"busLineId":"26","time":"13:51","direction":"Мале Пчелице (С. Село)-Теферич (Викенд Нас.)"},{"busLineId":"26","time":"14:51","direction":"Мале Пчелице (С. Село)-Теферич (Викенд Нас.)"},{"busLineId":"26","time":"15:41","direction":"Мале Пчелице (С. Село)-Теферич (Викенд Нас.)"},{"busLineId":"26","time":"16:41","direction":"Мале Пчелице (С. Село)-Теферич (Викенд Нас.)"},{"busLineId":"26","time":"18:41","direction":"Мале Пчелице (С. Село)-Теферич (Викенд Нас.)"},{"busLineId":"26","time":"20:36","direction":"Мале Пчелице (С. Село)-Теферич (Викенд Нас.)"},{"busLineId":"26","time":"22:36","direction":"Мале Пчелице (С. Село)-Теферич (Викенд Нас.)"}],"busDepartureB":[]}