{"busDepartureA":[{"busLineId":"2","time":"06:37","direction":"Нови Милановац-Доња Сабанта"},{"busLineId":"2","time":"07:23","direction":"Петровац-Доња Сабанта"},{"busLineId":"2","time":"08:03","direction":"Петровац-Ждраљица"},{"busLineId":"2","time":"08:58","direction":"Петровац-Доња Сабанта"},{"busLineId":"2","time":"09:47","direction":"Нови Милановац-Ждраљица"},{"busLineId":"2","time":"10:38","direction":"Петровац-Ждраљица"},{"busLineId":"2","time":"11:23","direction":"Петровац-Ждраљица"},{"busLineId":"2","time":"12:18","direction":"Петровац-Доња Сабанта"},{"busLineId":"2","time":"13:03","direction":"Петровац-Ждраљица"},{"busLineId":"2","time":"13:48","direction":"Петровац-Ждраљица"},{"busLineId":"2","time":"14:33","direction":"Петровац-Ждраљица"},{"busLineId":"2","time":"15:28","direction":"Петровац-Доња Сабанта"},{"busLineId":"2","time":"16:18","direction":"Петровац-Ждраљица"},{"busLineId":"2","time":"17:08","direction":"Петровац-Ждраљица"},{"busLineId":"2","time":"17:58","direction":"Петровац-Ждраљица"},{"busLineId":"2","time":"18:48","direction":"Петровац-Доња Сабанта"},{"busLineId":"2","time":"19:37","direction":"Нови Милановац-Ждраљица"},{"busLineId":"2","time":"20:38","direction":"Петровац-Доња Сабанта"},{"busLineId":"2","time":"21:23","direction":"Петровац-Ждраљица"},{"busLineId":"600","time":"06:40","direction":"Аутобуска станица-Први Ракаљ"},{"busLineId":"600","time":"19:10","direction":"Аутобуска станица-Први Ракаљ"}],"busDepartureB":[{"busLineId":"2","time":"06:12","direction":"Ждраљица-Петровац"},{"busLineId":"2","time":"06:51","direction":"Доња Сабанта-Петровац"},{"busLineId":"2","time":"07:41","direction":"Доња Сабанта-Петровац"},{"busLineId":"2","time":"08:27","direction":"Ждраљица-Нови Милановац"},{"busLineId":"2","time":"09:16","direction":"Доња Сабанта-Петровац"},{"busLineId":"2","time":"10:07","direction":"Ждраљица-Петровац"},{"busLineId":"2","time":"10:57","direction":"Ждраљица-Петровац"},{"busLineId":"2","time":"11:47","direction":"Ждраљица-Петровац"},{"busLineId":"2","time":"12:36","direction":"Доња Сабанта-Петровац"},{"busLineId":"2","time":"13:17","direction":"Ждраљица-Петровац"},{"busLineId":"2","time":"14:02","direction":"Ждраљица-Петровац"},{"busLineId":"2","time":"15:02","direction":"Ждраљица-Петровац"},{"busLineId":"2","time":"15:51","direction":"Доња Сабанта-Петровац"},{"busLineId":"2","time":"16:37","direction":"Ждраљица-Петровац"},{"busLineId":"2","time":"17:27","direction":"Ждраљица-Петровац"},{"busLineId":"2","time":"18:17","direction":"Ждраљица-Нови Милановац"},{"busLineId":"2","time":"19:16","direction":"Доња Сабанта-Петровац"},{"busLineId":"2","time":"19:57","direction":"Ждраљица-Петровац"},{"busLineId":"2","time":"21:11","direction":"Доња Сабанта-Петровац"},{"busLineId":"600","time":"07:31","direction":"Први Ракаљ-Велика сугубина - Крагујевац"},{"busLineId":"600","time":"20:01","direction":"Први Ракаљ-Велика сугубина - Крагујевац"}]}