{"busDepartureA":[],"busDepartureB":[{"busLineId":"16","time":"04:58","direction":"Село-Велико Поље"},{"busLineId":"16","time":"05:48","direction":"Село-Велико Поље"},{"busLineId":"16","time":"06:43","direction":"Село-Велико Поље"},{"busLineId":"16","time":"07:38","direction":"Село-Велико Поље"},{"busLineId":"16","time":"09:48","direction":"Село-Велико Поље"},{"busLineId":"16","time":"12:23","direction":"Село-Велико Поље"},{"busLineId":"16","time":"13:23","direction":"Село-Велико Поље"},{"busLineId":"16","time":"15:18","direction":"Село-Велико Поље"},{"busLineId":"16","time":"16:08","direction":"Село-Велико Поље"},{"busLineId":"16","time":"21:08","direction":"Село-Велико Поље"},{"busLineId":"16","time":"23:13","direction":"Село-Велико Поље"}]}