{"busDepartureA":[{"busLineId":"24","time":"05:55","direction":"Ћава-Кошутњак Брдо"},{"busLineId":"24","time":"06:45","direction":"Ћава-Кошутњак Брдо"},{"busLineId":"24","time":"07:20","direction":"Ћава-Кошутњак Брдо"},{"busLineId":"24","time":"07:55","direction":"Ћава-Кошутњак Брдо"},{"busLineId":"24","time":"09:05","direction":"Ћава-Кошутњак Брдо"},{"busLineId":"24","time":"10:20","direction":"Ћава-Кошутњак Брдо"},{"busLineId":"24","time":"11:50","direction":"Ћава-Кошутњак Брдо"},{"busLineId":"24","time":"13:05","direction":"Ћава-Кошутњак Брдо"},{"busLineId":"24","time":"13:35","direction":"Ћава-Кошутњак Брдо"},{"busLineId":"24","time":"14:25","direction":"Ћава-Кошутњак Брдо"},{"busLineId":"24","time":"15:00","direction":"Ћава-Кошутњак Брдо"},{"busLineId":"24","time":"15:35","direction":"Ћава-Кошутњак Брдо"},{"busLineId":"24","time":"16:40","direction":"Ћава-Кошутњак Брдо"},{"busLineId":"24","time":"17:30","direction":"Ћава-Кошутњак Брдо"},{"busLineId":"24","time":"18:40","direction":"Ћава-Кошутњак Брдо"},{"busLineId":"24","time":"19:55","direction":"Ћава-Кошутњак Брдо"},{"busLineId":"24","time":"21:05","direction":"Ћава-Кошутњак Брдо"},{"busLineId":"24","time":"22:40","direction":"Ћава-Кошутњак Брдо"}],"busDepartureB":[{"busLineId":"24","time":"05:06","direction":"Кошутњак Брдо-Ћава"},{"busLineId":"24","time":"06:16","direction":"Кошутњак Брдо-Ћава"},{"busLineId":"24","time":"06:51","direction":"Кошутњак Брдо-Ћава"},{"busLineId":"24","time":"07:26","direction":"Кошутњак Брдо-Ћава"},{"busLineId":"24","time":"08:01","direction":"Кошутњак Брдо-Ћава"},{"busLineId":"24","time":"09:11","direction":"Кошутњак Брдо-Ћава"},{"busLineId":"24","time":"10:31","direction":"Кошутњак Брдо-Ћава"},{"busLineId":"24","time":"12:01","direction":"Кошутњак Брдо-Ћава"},{"busLineId":"24","time":"12:36","direction":"Кошутњак Брдо-Ћава"},{"busLineId":"24","time":"13:16","direction":"Кошутњак Брдо-Ћава"},{"busLineId":"24","time":"13:56","direction":"Кошутњак Брдо-Ћава"},{"busLineId":"24","time":"14:31","direction":"Кошутњак Брдо-Ћава"},{"busLineId":"24","time":"15:06","direction":"Кошутњак Брдо-Ћава"},{"busLineId":"24","time":"15:56","direction":"Кошутњак Брдо-Ћава"},{"busLineId":"24","time":"17:36","direction":"Кошутњак Брдо-Ћава"},{"busLineId":"24","time":"18:46","direction":"Кошутњак Брдо-Ћава"},{"busLineId":"24","time":"20:01","direction":"Кошутњак Брдо-Ћава"},{"busLineId":"24","time":"21:11","direction":"Кошутњак Брдо-Ћава"}]}