{"busDepartureA":[{"busLineId":"611","time":"06:29","direction":"Крагујевац-Лужнице"},{"busLineId":"611","time":"08:09","direction":"Крагујевац-Лужнице"},{"busLineId":"611","time":"10:09","direction":"Крагујевац-Лужнице"},{"busLineId":"611","time":"12:19","direction":"Крагујевац-Лужнице"},{"busLineId":"611","time":"14:44","direction":"Крагујевац-Лужнице"},{"busLineId":"611","time":"16:29","direction":"Крагујевац-Лужнице"},{"busLineId":"611","time":"20:09","direction":"Крагујевац-Лужнице"},{"busLineId":"611","time":"22:59","direction":"Крагујевац-Лужнице"},{"busLineId":"613","time":"06:20","direction":"Крагујевац-Лужнице - Мала Врбица"},{"busLineId":"613","time":"13:00","direction":"Крагујевац-Лужнице - Мала Врбица"}],"busDepartureB":[{"busLineId":"611","time":"04:55","direction":"Лужнице-Церовац Село - Крагујевац"},{"busLineId":"611","time":"06:35","direction":"Лужнице-Церовац Село - Крагујевац"},{"busLineId":"611","time":"08:35","direction":"Лужнице-Крагујевац"},{"busLineId":"611","time":"10:30","direction":"Лужнице-Крагујевац"},{"busLineId":"611","time":"12:30","direction":"Лужнице-Церовац Село - Крагујевац"},{"busLineId":"611","time":"15:00","direction":"Лужнице-Крагујевац"},{"busLineId":"611","time":"16:45","direction":"Лужнице-Крагујевац"},{"busLineId":"611","time":"20:30","direction":"Лужнице-Крагујевац"},{"busLineId":"611","time":"23:00","direction":"Лужнице-Крагујевац"},{"busLineId":"613","time":"07:03","direction":"Мала Врбица-Лужнице - Крагујевац"},{"busLineId":"613","time":"13:48","direction":"Мала Врбица-Лужнице - Крагујевац"}]}