{"busDepartureA":[{"busLineId":"8","time":"08:26","direction":"Багремар-Стара Општина"},{"busLineId":"8","time":"10:26","direction":"Багремар-Илићево Споменик"},{"busLineId":"8","time":"12:26","direction":"Багремар-Илићево Споменик"},{"busLineId":"8","time":"18:26","direction":"Багремар-Илићево Споменик"},{"busLineId":"8","time":"20:26","direction":"Багремар-Стара Општина"}],"busDepartureB":[{"busLineId":"8","time":"07:54","direction":"Стара Општина-Багремар"},{"busLineId":"8","time":"09:54","direction":"Стара Општина-Багремар"},{"busLineId":"8","time":"11:55","direction":"Илићево Споменик-Багремар"},{"busLineId":"8","time":"17:54","direction":"Стара Општина-Багремар"},{"busLineId":"8","time":"19:55","direction":"Илићево Споменик-Багремар"}]}